{
  "adiye_chicken": {
    "displayText": "adìyẹ",
    "syllables": [
      "a",
      "dì",
      "yẹ"
    ],
    "definition": "chicken",
    "imageStyles": []
  },
  "agemo_july": {
    "displayText": "Agẹmọ",
    "syllables": [
      "a",
      "gẹ",
      "mọ"
    ],
    "definition": "July, the second month of the traditional Yoruba calendar, the Kọ́jọ́dá; the Agẹmọ festival is held during this month",
    "imageStyles": [
      "cartoon"
    ]
  },
  "agunfon_giraffe": {
    "displayText": "àgùnfon",
    "syllables": [
      "à",
      "gùn",
      "fọn"
    ],
    "definition": "giraffe (traditionally, giraffes did not live in the range of Yorubaland)",
    "imageStyles": []
  },
  "aja_dog": {
    "displayText": "ajá",
    "syllables": [
      "a",
      "já"
    ],
    "definition": "dog",
    "imageStyles": [
      "cartoon"
    ]
  },
  "alangba_lizard": {
    "displayText": "aláǹgbá",
    "syllables": [
      "a",
      "lá",
      "ǹ",
      "gbá"
    ],
    "definition": "lizard",
    "imageStyles": [
      "cartoon"
    ]
  },
  "alubosa_onion": {
    "displayText": "àlùbọ́sà",
    "syllables": [
      "à",
      "lù",
      "bọ́",
      "sà"
    ],
    "definition": "onion",
    "imageStyles": []
  },
  "aso_cloth": {
    "displayText": "aṣọ",
    "syllables": [
      "a",
      "ṣọ"
    ],
    "definition": "any cloth, fabric, textile",
    "imageStyles": [
      "cartoon"
    ]
  },
  "awo_plate": {
    "displayText": "àwo",
    "syllables": [
      "à",
      "wo"
    ],
    "definition": "dish, plate",
    "imageStyles": [
      "cartoon"
    ]
  },
  "aya_chest": {
    "displayText": "àyà",
    "syllables": [
      "à",
      "yà"
    ],
    "definition": "chest",
    "imageStyles": [
      "cartoon"
    ]
  },
  "baluwe_bathroom": {
    "displayText": "balùwẹ̀",
    "syllables": [
      "ba",
      "lù",
      "wẹ̀"
    ],
    "definition": "bathroom",
    "imageStyles": [
      "cartoon"
    ]
  },
  "beelu_november": {
    "displayText": "Beélú",
    "syllables": [
      "be",
      "é",
      "lú"
    ],
    "definition": "November, the sixth month of the traditional Yoruba calendar, the Kọ́jọ́dá",
    "imageStyles": [
      "cartoon"
    ]
  },
  "buredi_bread": {
    "displayText": "búrẹ́dì",
    "syllables": [
      "bú",
      "rẹ́",
      "dì"
    ],
    "definition": "bread",
    "imageStyles": []
  },
  "dide_stand": {
    "displayText": "dìde",
    "syllables": [
      "dì",
      "de"
    ],
    "definition": "to stand, get up, rise",
    "imageStyles": [
      "cartoon"
    ]
  },
  "digi_mirror": {
    "displayText": "dígí",
    "syllables": [
      "dí",
      "gí"
    ],
    "definition": "mirror, glass",
    "imageStyles": []
  },
  "ebibi_may": {
    "displayText": "Èbìbí",
    "syllables": [
      "è",
      "bì",
      "bí"
    ],
    "definition": "May, the twelfth and final month in the Yoruba calendar, the Kọ́jọ́dá, during which the Ẹ̀bìbì festival is usually celebrated in.",
    "imageStyles": [
      "cartoon"
    ]
  },
  "eekanna_nail": {
    "displayText": "èékánná",
    "syllables": [
      "è",
      "é",
      "kán",
      "ná"
    ],
    "definition": "nail (may refer to nails of either the toe or finger), claw",
    "imageStyles": [
      "cartoon"
    ]
  },
  "ejika_shoulder": {
    "displayText": "ejika",
    "syllables": [
      "e",
      "ji",
      "ka"
    ],
    "definition": "shoulder",
    "imageStyles": [
      "cartoon"
    ]
  },
  "e_joo_please": {
    "displayText": "ẹ jọ̀ọ́",
    "syllables": [
      "ẹ",
      "jọ̀",
      "ọ́"
    ],
    "definition": "Please",
    "imageStyles": [
      "cartoon"
    ]
  },
  "ejo_snake": {
    "displayText": "ejò",
    "syllables": [
      "e",
      "jò"
    ],
    "definition": "snake",
    "imageStyles": [
      "cartoon"
    ]
  },
  "enu_mouth": {
    "displayText": "ẹnu",
    "syllables": [
      "ẹ",
      "nu"
    ],
    "definition": "mouth",
    "imageStyles": [
      "cartoon"
    ]
  },
  "erele_february": {
    "displayText": "Èrèlé",
    "syllables": [
      "è",
      "rè",
      "lé"
    ],
    "definition": "February, the ninth month in the traditional Yoruba calendar, the Kọ́jọ́dá",
    "imageStyles": [
      "cartoon"
    ]
  },
  "erena_march": {
    "displayText": "Ẹrénà",
    "syllables": [
      "ẹ",
      "ré",
      "nà"
    ],
    "definition": "March, the tenth month in the Yoruba calendar, the Kọ́jọ́dá",
    "imageStyles": [
      "cartoon"
    ]
  },
  "ese_leg": {
    "displayText": "ẹsẹ̀",
    "syllables": [
      "ẹ",
      "sẹ̀"
    ],
    "definition": "foot, leg",
    "imageStyles": [
      "cartoon"
    ]
  },
  "esin_horse": {
    "displayText": "ẹṣin",
    "syllables": [
      "ẹ",
      "ṣin"
    ],
    "definition": "horse",
    "imageStyles": [
      "cartoon"
    ]
  },
  "esinsin_fly": {
    "displayText": "eṣinṣin",
    "syllables": [
      "e",
      "ṣin",
      "ṣin"
    ],
    "definition": "housefly, fly (insect)",
    "imageStyles": []
  },
  "ete_lip": {
    "displayText": "ètè",
    "syllables": [
      "è",
      "tè"
    ],
    "definition": "lip",
    "imageStyles": [
      "cartoon"
    ]
  },
  "eti_ear": {
    "displayText": "etí",
    "syllables": [
      "e",
      "tí"
    ],
    "definition": "ear",
    "imageStyles": [
      "cartoon"
    ]
  },
  "ewa_beans": {
    "displayText": "èwà",
    "syllables": [
      "è",
      "wà"
    ],
    "definition": "A general name for beans, peas, and legumes, often specifically referring to the black-eyed pea",
    "imageStyles": [
      "cartoon"
    ]
  },
  "ewa_beauty": {
    "displayText": "ẹwà",
    "syllables": [
      "ẹ",
      "wà"
    ],
    "definition": "beauty, attraction",
    "imageStyles": [
      "cartoon"
    ]
  },
  "ewe_leaf": {
    "displayText": "ewé",
    "syllables": [
      "e",
      "wé"
    ],
    "definition": "leaf, foliage",
    "imageStyles": [
      "cartoon"
    ]
  },
  "eye_bird": {
    "displayText": "ẹyẹ",
    "syllables": [
      "ẹ",
      "yẹ"
    ],
    "definition": "bird",
    "imageStyles": [
      "cartoon"
    ]
  },
  "eyin_back": {
    "displayText": "ẹ̀yìn",
    "syllables": [
      "ẹ̀",
      "yìn"
    ],
    "definition": "back",
    "imageStyles": [
      "cartoon"
    ]
  },
  "fo_break": {
    "displayText": "fọ́",
    "syllables": [
      "fọ́"
    ],
    "definition": null,
    "imageStyles": []
  },
  "goomu_gum": {
    "displayText": "gọ́ọ̀mù",
    "syllables": [
      "gọ́",
      "ọ̀",
      "mù"
    ],
    "definition": null,
    "imageStyles": []
  },
  "guafa_guava": {
    "displayText": "gúáfà",
    "syllables": [
      "gú",
      "á",
      "fà"
    ],
    "definition": null,
    "imageStyles": []
  },
  "ibepe_papaya": {
    "displayText": "ìbẹ́pẹ",
    "syllables": [
      "ì",
      "bẹ́",
      "pẹ"
    ],
    "definition": "papaya",
    "imageStyles": []
  },
  "ibusun_bed": {
    "displayText": "ibùsùn",
    "syllables": [
      "i",
      "bù",
      "sùn"
    ],
    "definition": "bed",
    "imageStyles": [
      "cartoon"
    ]
  },
  "idodo_navel": {
    "displayText": "idodo",
    "syllables": [
      "i",
      "do",
      "do"
    ],
    "definition": "navel, belly button",
    "imageStyles": [
      "cartoon"
    ]
  },
  "ifoyin_toothbrush": {
    "displayText": "ìfọyín",
    "syllables": [
      "ì",
      "fọ",
      "yín"
    ],
    "definition": null,
    "imageStyles": []
  },
  "igbe_april": {
    "displayText": "Igbe",
    "syllables": [
      "i",
      "gbe"
    ],
    "definition": "April, the eleventh month in the Yoruba calendar, the Kọ́jọ́dá",
    "imageStyles": [
      "cartoon"
    ]
  },
  "igbo_forest": {
    "displayText": "igbó",
    "syllables": [
      "i",
      "gbó"
    ],
    "definition": "forest, bush, grove",
    "imageStyles": [
      "cartoon"
    ]
  },
  "ikoko_pot": {
    "displayText": "ìkòkò",
    "syllables": [
      "ì",
      "kò",
      "kò"
    ],
    "definition": "pot, multipurpose pot traditionally made of clay.",
    "imageStyles": [
      "cartoon"
    ]
  },
  "ikun_stomach": {
    "displayText": "ikùn",
    "syllables": [
      "i",
      "kùn"
    ],
    "definition": "abdomen, belly",
    "imageStyles": [
      "cartoon"
    ]
  },
  "ile_home": {
    "displayText": "ilé",
    "syllables": [
      "i",
      "lé"
    ],
    "definition": "home, house, abode",
    "imageStyles": []
  },
  "ilekun_door": {
    "displayText": "ìlẹ̀kùn",
    "syllables": [
      "ì",
      "lẹ̀",
      "kùn"
    ],
    "definition": "door",
    "imageStyles": [
      "cartoon"
    ]
  },
  "imu_nose": {
    "displayText": "imú",
    "syllables": [
      "i",
      "mú"
    ],
    "definition": "nose",
    "imageStyles": [
      "cartoon"
    ]
  },
  "ina_fire": {
    "displayText": "iná",
    "syllables": [
      "i",
      "ná"
    ],
    "definition": "fire, light",
    "imageStyles": []
  },
  "inu_inside": {
    "displayText": "inú",
    "syllables": [
      "i",
      "nú"
    ],
    "definition": null,
    "imageStyles": []
  },
  "inura_towel": {
    "displayText": "ìnura",
    "syllables": [
      "ì",
      "nu",
      "ra"
    ],
    "definition": null,
    "imageStyles": []
  },
  "irawo_star": {
    "displayText": "ìràwọ̀",
    "syllables": [
      "ì",
      "rà",
      "wọ̀"
    ],
    "definition": "star, celestial object, celestial body",
    "imageStyles": []
  },
  "irin_iron": {
    "displayText": "irin",
    "syllables": [
      "i",
      "rin"
    ],
    "definition": "metal (in particular) iron",
    "imageStyles": [
      "cartoon"
    ]
  },
  "irin_walk": {
    "displayText": "ìrìn",
    "syllables": [
      "ì",
      "rìn"
    ],
    "definition": "walk; stroll",
    "imageStyles": [
      "cartoon"
    ]
  },
  "itan_thigh": {
    "displayText": "itan",
    "syllables": [
      "i",
      "tan"
    ],
    "definition": "thigh",
    "imageStyles": [
      "cartoon"
    ]
  },
  "jeun_eat": {
    "displayText": "jẹun",
    "syllables": [
      "jẹ",
      "un"
    ],
    "definition": "to eat food",
    "imageStyles": [
      "cartoon"
    ]
  },
  "jokoo_sit": {
    "displayText": "jókòó",
    "syllables": [
      "jó",
      "kò",
      "ó"
    ],
    "definition": "to sit (down)",
    "imageStyles": []
  },
  "kalamu_pen": {
    "displayText": "kálàmú",
    "syllables": [
      "ká",
      "là",
      "mú"
    ],
    "definition": "pen (writing tool)",
    "imageStyles": []
  },
  "kasu_cashew": {
    "displayText": "kaṣú",
    "syllables": [
      "ka",
      "ṣú"
    ],
    "definition": null,
    "imageStyles": []
  },
  "lo_go": {
    "displayText": "lọ",
    "syllables": [
      "lọ"
    ],
    "definition": "to go",
    "imageStyles": [
      "cartoon"
    ]
  },
  "maluu_cow": {
    "displayText": "màlúù",
    "syllables": [
      "mà",
      "lú",
      "ù"
    ],
    "definition": "cow, ox, cattle; (in particular) zebu cow",
    "imageStyles": []
  },
  "moto_automobile": {
    "displayText": "mọ́tò",
    "syllables": [
      "mọ́",
      "tò"
    ],
    "definition": "car",
    "imageStyles": []
  },
  "oba_king": {
    "displayText": "ọba",
    "syllables": [
      "ọ",
      "ba"
    ],
    "definition": "king, queen, monarch",
    "imageStyles": []
  },
  "obe_knife": {
    "displayText": "ọ̀bẹ",
    "syllables": [
      "ọ̀",
      "bẹ"
    ],
    "definition": "knife, blade",
    "imageStyles": []
  },
  "oduduwa_oduduwa": {
    "displayText": "odùduwà",
    "syllables": [
      "o",
      "dù",
      "du",
      "wà"
    ],
    "definition": "The legendary ruler (Ọọ̀ni) of Ifẹ̀, he waged a war with Ọbàtálá and gained control of Ifẹ̀, where he became Ọọ̀ni. Because of this and his many descendants who founded modern Yoruba settlements, he is regarded as the father of the Yorùbá people",
    "imageStyles": []
  },
  "ogbon_wisdom": {
    "displayText": "ọgbọ́n",
    "syllables": [
      "ọ",
      "gbọ́n"
    ],
    "definition": "wisdom; sense",
    "imageStyles": []
  },
  "ogede_banana": {
    "displayText": "ọ̀gẹ̀dè",
    "syllables": [
      "ọ̀",
      "gẹ̀",
      "dè"
    ],
    "definition": "banana, plantain",
    "imageStyles": []
  },
  "ogun_august": {
    "displayText": "Ògún",
    "syllables": [
      "ò",
      "gún"
    ],
    "definition": "August, the third month of the traditional Yoruba calendar, the Kọ́jọ́dá; named in honor of Ògún. Many Ògún festivals are held during this month.",
    "imageStyles": [
      "cartoon"
    ]
  },
  "ogun_twenty": {
    "displayText": "ogún",
    "syllables": [
      "o",
      "gún"
    ],
    "definition": "twenty",
    "imageStyles": []
  },
  "oja_market": {
    "displayText": "ọjà",
    "syllables": [
      "ọ",
      "jà"
    ],
    "definition": "market",
    "imageStyles": []
  },
  "ojo_day": {
    "displayText": "ọjọ́",
    "syllables": [
      "ọ",
      "jọ́"
    ],
    "definition": "day",
    "imageStyles": [
      "cartoon"
    ]
  },
  "oju_eye": {
    "displayText": "ojú",
    "syllables": [
      "o",
      "jú"
    ],
    "definition": "eye",
    "imageStyles": [
      "cartoon"
    ]
  },
  "okudu_june": {
    "displayText": "Okúdù",
    "syllables": [
      "o",
      "kú",
      "dù"
    ],
    "definition": "June, the first month of the traditional Yoruba calendar, the Kọ́jọ́dá",
    "imageStyles": [
      "cartoon"
    ]
  },
  "okuta_stone": {
    "displayText": "òkúta",
    "syllables": [
      "ò",
      "kú",
      "ta"
    ],
    "definition": "rock, stone",
    "imageStyles": []
  },
  "olongbo_cat": {
    "displayText": "olóńgbò",
    "syllables": [
      "o",
      "ló",
      "ń",
      "gbò"
    ],
    "definition": "cat",
    "imageStyles": []
  },
  "ookan_one": {
    "displayText": "oókan",
    "syllables": [
      "o",
      "ó",
      "kan"
    ],
    "definition": "one (used when counting)",
    "imageStyles": []
  },
  "ope_december": {
    "displayText": "Ọ̀pẹ",
    "syllables": [
      "ọ̀",
      "pẹ"
    ],
    "definition": "December, the seventh month of the traditional Yoruba calendar, the Kọ́jọ́dá",
    "imageStyles": [
      "cartoon"
    ]
  },
  "ori_head": {
    "displayText": "orí",
    "syllables": [
      "o",
      "rí"
    ],
    "definition": "head",
    "imageStyles": [
      "cartoon"
    ]
  },
  "orun_neck": {
    "displayText": "ọrùn",
    "syllables": [
      "ọ",
      "rùn"
    ],
    "definition": "neck",
    "imageStyles": [
      "cartoon"
    ]
  },
  "osan_orange": {
    "displayText": "ọsàn",
    "syllables": [
      "ọ",
      "sàn"
    ],
    "definition": "orange (fruit)",
    "imageStyles": []
  },
  "ose_soap": {
    "displayText": "ọṣẹ",
    "syllables": [
      "ọ",
      "ṣẹ"
    ],
    "definition": "soap",
    "imageStyles": [
      "cartoon"
    ]
  },
  "osupa_moon": {
    "displayText": "òṣùpá",
    "syllables": [
      "ò",
      "ṣù",
      "pá"
    ],
    "definition": "moon",
    "imageStyles": []
  },
  "owawa_october": {
    "displayText": "Ọ̀wàwà",
    "syllables": [
      "ọ̀",
      "wà",
      "wà"
    ],
    "definition": null,
    "imageStyles": [
      "cartoon"
    ]
  },
  "owewe_september": {
    "displayText": "Ọwẹ́wẹ",
    "syllables": [
      "ọ",
      "wẹ́",
      "wẹ"
    ],
    "definition": "September, the third month of the traditional Yoruba calendar, the Kọ́jọ́dá",
    "imageStyles": [
      "cartoon"
    ]
  },
  "owo_hand": {
    "displayText": "ọwọ",
    "syllables": [
      "ọ",
      "wọ"
    ],
    "definition": "hand",
    "imageStyles": [
      "cartoon"
    ]
  },
  "pako_timber": {
    "displayText": "pákó",
    "syllables": [
      "pá",
      "kó"
    ],
    "definition": "wood, plank, wooden board",
    "imageStyles": []
  },
  "pele_sorry": {
    "displayText": "pẹ̀lẹ́",
    "syllables": [
      "pẹ̀",
      "lẹ́"
    ],
    "definition": "sorry (used to apologize or express condolence)",
    "imageStyles": [
      "cartoon"
    ]
  },
  "pepeye_duck": {
    "displayText": "pẹ́pẹ́yẹ",
    "syllables": [
      "pẹ́",
      "pẹ́",
      "yẹ"
    ],
    "definition": "duck",
    "imageStyles": [
      "cartoon"
    ]
  },
  "ra_crawl": {
    "displayText": "rá",
    "syllables": [
      "rá"
    ],
    "definition": "to crawl",
    "imageStyles": [
      "cartoon"
    ]
  },
  "redio_radio": {
    "displayText": "rédíò",
    "syllables": [
      "ré",
      "dí",
      "ò"
    ],
    "definition": null,
    "imageStyles": []
  },
  "sare_run": {
    "displayText": "sáré",
    "syllables": [
      "sá",
      "ré"
    ],
    "definition": "to run",
    "imageStyles": [
      "cartoon"
    ]
  },
  "seere_january": {
    "displayText": "Ṣẹẹrẹ",
    "syllables": [
      "ṣẹ",
      "ẹ",
      "rẹ"
    ],
    "definition": null,
    "imageStyles": [
      "cartoon"
    ]
  },
  "sibi_spoon": {
    "displayText": "ṣíbí",
    "syllables": [
      "ṣí",
      "bí"
    ],
    "definition": "spoon",
    "imageStyles": []
  },
  "wa_come": {
    "displayText": "wá",
    "syllables": [
      "wá"
    ],
    "definition": "come",
    "imageStyles": [
      "cartoon"
    ]
  }
}